pynetbrain.py
pynetbrain-0.1.2.dist-info/LICENSE
pynetbrain-0.1.2.dist-info/METADATA
pynetbrain-0.1.2.dist-info/WHEEL
pynetbrain-0.1.2.dist-info/top_level.txt
pynetbrain-0.1.2.dist-info/RECORD
